yls_yara/__init__.py
yls_yara/linting.py
yls_yara-1.4.4.dist-info/LICENSE
yls_yara-1.4.4.dist-info/METADATA
yls_yara-1.4.4.dist-info/WHEEL
yls_yara-1.4.4.dist-info/entry_points.txt
yls_yara-1.4.4.dist-info/RECORD
