Metadata-Version: 2.3
Name: yls-yara
Version: 1.4.4
Summary: YLS plugin adding linting using yara-python.
License: MIT
Author: Matej Kastak
Author-email: matej.kastak@avast.com
Maintainer: Matej Kašťák
Maintainer-email: matej.kastak@avast.com
Requires-Python: >=3.8,<4.0
Classifier: License :: OSI Approved :: MIT License
Classifier: Programming Language :: Python :: 3
Classifier: Programming Language :: Python :: 3.8
Classifier: Programming Language :: Python :: 3.9
Classifier: Programming Language :: Python :: 3.10
Classifier: Programming Language :: Python :: 3.11
Classifier: Programming Language :: Python :: 3.12
Classifier: Programming Language :: Python :: 3.13
Requires-Dist: yara-python (>=4.5.1,<5.0.0)
Requires-Dist: yls (>=1.4.4,<2.0.0)
